.gitignore
.travis.yml
CHANGES.rst
CODE_OF_CONDUCT.md
CONTRIBUTING.md
LICENSE.rst
README.rst
setup.cfg
setup.py
tox.ini
jwstinfo/__init__.py
jwstinfo/jwstinfo.py
jwstinfo.egg-info/PKG-INFO
jwstinfo.egg-info/SOURCES.txt
jwstinfo.egg-info/dependency_links.txt
jwstinfo.egg-info/entry_points.txt
jwstinfo.egg-info/not-zip-safe
jwstinfo.egg-info/requires.txt
jwstinfo.egg-info/top_level.txt