Metadata-Version: 1.2
Name: jwstinfo
Version: 0.1.0
Summary: Provides summary of JWST data files
Home-page: https://github.com/spacetelescope/jwstinfo
Author: Daniel D'Avella
Author-email: ddavella@stsci.edu
License: BSD 3-Clause
Platform: UNKNOWN
Provides: jwstinfo
Requires-Python: >=3.6
